projekt sterownik linuxowy/gpioemu.v
/* verilator lint_off UNUSED */ 
/* verilator lint_off UNDRIVEN */ 
/* verilator lint_off MULTIDRIVEN */ 
/* verilator lint_off COMBDLY */
/* verilator lint_off WIDTH */
/* verilator lint_off CASEINCOMPLETE */
module gpioemu(n_reset,                 //magistrala z CPU
    saddress[15:0], srd, swr, 
    sdata_in[31:0], sdata_out[31:0], 
    gpio_in[31:0], gpio_latch,          //styk z GPIO - in
    gpio_out[31:0],                     //styk z GPIO = out
    clk,                                //sygnaly opcjonalne - zegar 1 KHz
    gpio_in_s_insp[31:0]);              //sygnaly testowe

    input           clk;
    input           n_reset;
    input [15:0]    saddress;       //magistrala - adres
    input           srd;            //odczyt przez CPU z mag. danych
    input           swr;            //zapis przez CPU do mag. danych 
    input [31:0]    sdata_in;       //magistrala wejsciowa CPU
    output[31:0]    sdata_out;      //magistrala wyjsciowa z CPU
    reg [31:0]        sdata_out_s;    //stan magistrali danych -wyjscie
    input[31:0]     gpio_in;          //dane z peryferii wejscie do modulu
    reg[31:0]         gpio_in_s;        //stan peryferii wyjsciowych
    input             gpio_latch;        //zapis danych na gpio_in
    output[31:0]    gpio_in_s_insp; //debuging
    output[31:0]    gpio_out;          //dane wyjsciowedo peryferii
    reg[31:0]       gpio_out_s;      //stan peryferii wejsciowych

    reg[31:0]        sdata_in_s;

   
    
    parameter MAX_PRIME = 1000;
    parameter IDLE = 2'b00;
    parameter CALCULATING = 2'b01;
    parameter CHECKING_PRIME = 2'b11;
    parameter FOUND = 2'b10;

    reg unsigned [9:0] A;
    reg unsigned [2:0] S;
    reg unsigned [31:0] W;
    reg unsigned [31:0] number_of_numbers;
    reg unsigned [31:0] current_prime;


    reg unsigned [31:0] prime_count;
    reg unsigned [31:0] i;
    reg prime_flag;

    always @(negedge n_reset)
    begin
        gpio_in_s <= 0;
        gpio_out_s <= 0;
        sdata_out_s <= 0;
        A <= 0;
        S <= IDLE;
        W <= 0;
        number_of_numbers <= 0;
        prime_count <= 0;
        current_prime <= 2;
        i <= 0;
        prime_flag <= 1;
    end
    
    always @(posedge gpio_latch) begin
		gpio_in_s[31:0] <= gpio_in[31:0];
    end


    always @(posedge swr)
    begin
        if (saddress == 16'h288)
        begin
            W <= 0;
            A <= sdata_in[9:0];
            S <= CALCULATING;
            current_prime <= 2;
            prime_count <= 0;
        end
    end

    always @(posedge srd)
    begin
        if (saddress == 16'h288)
        begin
            sdata_out_s <= {22'b0, A[9:0]};
        end
        else if (saddress == 16'h2A0)
        begin
            sdata_out_s <= {29'b0, S[2:0]};
        end
        else if (saddress == 16'h298)
        begin
            sdata_out_s <= W;
        end
        else
        begin
            sdata_out_s <= 0;
        end
    end

    always @(posedge clk)
    begin
        case(S)
            IDLE:
            begin
                if (A != 0)
                begin
                    S <= CALCULATING;
                    current_prime <= 2;
                    prime_count <= 0;
                    number_of_numbers <= 0;
                end
            end
            CALCULATING:
            begin
                S <= CHECKING_PRIME;
                i <= 2;
                prime_flag <= 1;
            end
            CHECKING_PRIME:
            begin
                if (i * i > current_prime)
                begin
                    if (prime_flag)
                    begin
                        if (prime_count == A - 1)
                        begin
							current_prime <= current_prime + 1;
                            prime_count <= prime_count + 1;
                            number_of_numbers <= number_of_numbers + 1;
                            S <= FOUND;
                            W <= current_prime;
                        end
                        else
                        begin
                            current_prime <= current_prime + 1;
                            prime_count <= prime_count + 1;
                            number_of_numbers <= number_of_numbers + 1;
                            S <= CALCULATING;
                        end
                    end
                    else
                    begin
                        current_prime <= current_prime + 1;
                        S <= CALCULATING;
                    end
                end
                else
                begin
                    if (current_prime % i == 0)
                        prime_flag <= 0;
                    i <= i + 1;
                end
            end
            FOUND:
            begin
                prime_count <= 0;
                A <= 0;
                S <= IDLE;
            end
        endcase
    end

    always @(posedge clk)
    begin
        gpio_out_s <= number_of_numbers;
    
    end

    assign gpio_out = gpio_out_s;
    assign gpio_in_s_insp = gpio_in_s;
    assign sdata_out = sdata_out_s;

endmodule

projekt sterownik linuxowy/gpioemu_tb.v
`timescale 1ns/100ps
module gpioemu_tb;

	reg         n_reset;
	reg [15:0]  saddress;
	reg         srd;
	reg         swr;
	reg [31:0]  sdata_in;
	reg [31:0]  gpio_in;
	reg         gpio_latch;
	reg         clk = 1;
	wire [31:0] gpio_out;
	wire [31:0] sdata_out;
	wire [31:0] gpio_in_s_insp; 
initial begin
	$dumpfile("gpioemu.vcd");
	$dumpvars(0, gpioemu_tb);
end

initial begin
    forever begin
    # 5 clk = ~clk;
    end
end

initial begin
//testy czy poprawnie liczy
    # 5 n_reset = 1;
    # 5 n_reset = 0;
    # 5 saddress = 16'h288;
    # 5 sdata_in = 32'b00000000000000000000000000000100;
    # 5 swr = 1;
    # 5 swr = 0;
	# 4000
	//kolejny taki test
	# 5 saddress = 16'h288;
    # 5 sdata_in = 32'b00000000000000000000000000010100;
    # 5 swr = 1;
    # 5 swr = 0;
	# 4000
	// próba zapisania pod zły adres
	# 5 saddress = 16'h100;
	# 5 sdata_in = 32'b00000000000000000000000000010100;
	# 5 swr = 1;
	# 5 swr = 0;
	# 1000;
	//Odczytanie rejestru W
	# 50 saddress = 16'h298;
	# 50 srd = 1;
	# 5 srd = 0;
	//Odczytanie rejestruS
    # 5 saddress = 16'h288;
    # 5 sdata_in = 32'b00000000000000000000000000000100;
    # 5 swr = 1;
    # 5 swr = 0;
	# 50 saddress = 16'h2A0;
	# 50 srd = 1;
	# 5 srd = 0;
	# 4000
	//kolejny taki test
	# 5 saddress = 16'h288;
    # 5 sdata_in = 32'b00000000000000000000000000010100;
    # 5 swr = 1;
    # 5 swr = 0;
	//Odczytanie rejestru A
	# 50 saddress = 16'h288;
	# 50 srd = 1;
	# 5 srd = 0;
	# 4000
	//Próba odczytania ze złego rejestru
	# 50 saddress = 16'h124;
	# 50 srd = 1;
	# 5 srd = 0;
	
	
	
	
    # 2000 $finish;
end

gpioemu dut (n_reset, saddress, srd, swr, sdata_in, sdata_out, gpio_in, gpio_latch, gpio_out, clk, gpio_in_s_insp);

endmodule

projekt sterownik linuxowy/gpioemu.vcd
$date
	Sun Jun 02 20:19:40 2024
$end
$version
	Icarus Verilog
$end
$timescale
	100ps
$end
$scope module gpioemu_tb $end
$var wire 32 ! sdata_out [31:0] $end
$var wire 32 " gpio_out [31:0] $end
$var wire 32 # gpio_in_s_insp [31:0] $end
$var reg 1 $ clk $end
$var reg 32 % gpio_in [31:0] $end
$var reg 1 & gpio_latch $end
$var reg 1 ' n_reset $end
$var reg 16 ( saddress [15:0] $end
$var reg 32 ) sdata_in [31:0] $end
$var reg 1 * srd $end
$var reg 1 + swr $end
$scope module dut $end
$var wire 1 $ clk $end
$var wire 32 , gpio_in [31:0] $end
$var wire 32 - gpio_in_s_insp [31:0] $end
$var wire 1 & gpio_latch $end
$var wire 32 . gpio_out [31:0] $end
$var wire 1 ' n_reset $end
$var wire 16 / saddress [15:0] $end
$var wire 32 0 sdata_in [31:0] $end
$var wire 32 1 sdata_out [31:0] $end
$var wire 1 * srd $end
$var wire 1 + swr $end
$var parameter 2 2 CALCULATING $end
$var parameter 2 3 CHECKING_PRIME $end
$var parameter 2 4 FOUND $end
$var parameter 2 5 IDLE $end
$var parameter 32 6 MAX_PRIME $end
$var reg 10 7 A [9:0] $end
$var reg 3 8 S [2:0] $end
$var reg 32 9 W [31:0] $end
$var reg 32 : current_prime [31:0] $end
$var reg 32 ; gpio_in_s [31:0] $end
$var reg 32 < gpio_out_s [31:0] $end
$var reg 32 = i [31:0] $end
$var reg 32 > number_of_numbers [31:0] $end
$var reg 32 ? prime_count [31:0] $end
$var reg 1 @ prime_flag $end
$var reg 32 A sdata_out_s [31:0] $end
$upscope $end
$upscope $end
$enddefinitions $end
$comment Show the parameter values. $end
$dumpall
b1111101000 6
b0 5
b10 4
b11 3
b1 2
$end
#0
$dumpvars
bx A
x@
bx ?
bx >
bx =
bx <
bx ;
bx :
bx 9
bx 8
bx 7
bx 1
bx 0
bx /
bx .
bx -
bx ,
x+
x*
bx )
bx (
x'
x&
bx %
1$
bx #
bx "
bx !
$end
#50
1'
0$
#100
1@
b0 =
b10 :
b0 ?
b0 >
b0 9
b0 8
b0 7
b0 !
b0 1
b0 A
b0 "
b0 .
b0 <
b0 #
b0 -
b0 ;
0'
1$
#150
b1010001000 (
b1010001000 /
0$
#200
b100 )
b100 0
1$
#250
b1 8
b100 7
1+
0$
#300
b10 =
b11 8
0+
1$
#350
0$
#400
b1 8
b1 >
b1 ?
b11 :
1$
#450
0$
#500
b1 "
b1 .
b1 <
b11 8
1$
#550
0$
#600
b1 8
b10 >
b10 ?
b100 :
1$
#650
0$
#700
b10 "
b10 .
b10 <
b11 8
1$
#750
0$
#800
b11 =
0@
1$
#850
0$
#900
b1 8
b101 :
1$
#950
0$
#1000
1@
b10 =
b11 8
1$
#1050
0$
#1100
b11 =
1$
#1150
0$
#1200
b1 8
b11 >
b11 ?
b110 :
1$
#1250
0$
#1300
b11 "
b11 .
b11 <
b10 =
b11 8
1$
#1350
0$
#1400
b11 =
0@
1$
#1450
0$
#1500
b1 8
b111 :
1$
#1550
0$
#1600
1@
b10 =
b11 8
1$
#1650
0$
#1700
b11 =
1$
#1750
0$
#1800
b111 9
b10 8
b100 >
b100 ?
b1000 :
1$
#1850
0$
#1900
b100 "
b100 .
b100 <
b0 8
b0 7
b0 ?
1$
